setup.py
ddb_pop_n_lock.egg-info/PKG-INFO
ddb_pop_n_lock.egg-info/SOURCES.txt
ddb_pop_n_lock.egg-info/dependency_links.txt
ddb_pop_n_lock.egg-info/requires.txt
ddb_pop_n_lock.egg-info/top_level.txt
ddblocker/__init__.py