Metadata-Version: 1.0
Name: ddb-pop-n-lock
Version: 1.0.1
Summary: A simple reasonable lock for AWS dynamodb
Home-page: https://github.com/optimuspaul/ddb-pop-n-lock
Author: pjdecoursey
Author-email: rosie@robotlove.guru
License: MIT
Platform: UNKNOWN
